cdk_github_role/__init__.py
cdk_github_role/py.typed
cdk_github_role/_jsii/__init__.py
cdk_github_role/_jsii/cdk-github-role@0.0.5.jsii.tgz
cdk_github_role-0.0.5.dist-info/LICENSE
cdk_github_role-0.0.5.dist-info/METADATA
cdk_github_role-0.0.5.dist-info/NOTICE
cdk_github_role-0.0.5.dist-info/WHEEL
cdk_github_role-0.0.5.dist-info/top_level.txt
cdk_github_role-0.0.5.dist-info/RECORD
