Metadata-Version: 2.1
Name: cdk-github-role
Version: 0.0.5
Summary: IAM Role that can be assumed by GitHub workflows
Home-page: https://github.com:/dklabs/cdk-github-role.git
Author: Amazon Web Services
License: Apache-2.0
Project-URL: Source, https://github.com:/dklabs/cdk-github-role.git
Platform: UNKNOWN
Classifier: Intended Audience :: Developers
Classifier: Operating System :: OS Independent
Classifier: Programming Language :: JavaScript
Classifier: Programming Language :: Python :: 3 :: Only
Classifier: Programming Language :: Python :: 3.6
Classifier: Programming Language :: Python :: 3.7
Classifier: Programming Language :: Python :: 3.8
Classifier: Programming Language :: Python :: 3.9
Classifier: Typing :: Typed
Classifier: Development Status :: 5 - Production/Stable
Classifier: License :: OSI Approved
Requires-Python: >=3.6
License-File: LICENSE
License-File: NOTICE
Requires-Dist: aws-cdk.aws-iam (<2.0.0,>=1.127.0)
Requires-Dist: aws-cdk.core (<2.0.0,>=1.127.0)
Requires-Dist: constructs (<4.0.0,>=3.2.27)
Requires-Dist: jsii (<2.0.0,>=1.39.0)
Requires-Dist: publication (>=0.0.3)
